growwapi/LICENSE
growwapi/README.MD
growwapi/__init__.py
growwapi/common/__init__.py
growwapi/common/files.py
growwapi/groww/__init__.py
growwapi/groww/client.py
growwapi/groww/constants.py
growwapi/groww/exceptions.py
growwapi/groww/feed.py
growwapi/groww/nats_client.py
growwapi/groww/proto/__init__.py
growwapi/groww/proto/position_socket_pb2.py
growwapi/groww/proto/proto_parser.py
growwapi/groww/proto/stock_orders_socket_response_pb2.py
growwapi/groww/proto/stocks_socket_response_pb2.py
growwapi/poetry.lock
growwapi/pyproject.toml
growwapi-1.2.0.dist-info/LICENSE
growwapi-1.2.0.dist-info/METADATA
growwapi-1.2.0.dist-info/WHEEL
growwapi-1.2.0.dist-info/RECORD
