Metadata-Version: 2.3
Name: growwapi
Version: 1.2.0
Summary: The foundational SDK for accessing Groww APIs and listening to live data streams. This package provides the core functionalities required to interact with Groww's trading platform.
License: MIT
Author: Groww
Author-email: growwapi@groww.in
Requires-Python: >=3.9,<4.0
Classifier: License :: OSI Approved :: MIT License
Classifier: Programming Language :: Python :: 3
Classifier: Programming Language :: Python :: 3.9
Classifier: Programming Language :: Python :: 3.10
Classifier: Programming Language :: Python :: 3.11
Classifier: Programming Language :: Python :: 3.12
Classifier: Programming Language :: Python :: 3.13
Requires-Dist: aiohttp (>=3.11.18,<4.0.0)
Requires-Dist: certifi (>=2025.1.31,<2026.0.0)
Requires-Dist: clint (>=0.5.1,<0.6.0)
Requires-Dist: colorama (>=0.4.6,<0.5.0)
Requires-Dist: google (>=3.0.0,<4.0.0)
Requires-Dist: nats-py (>=2.9.0,<3.0.0)
Requires-Dist: nkeys (>=0.2.1,<0.3.0)
Requires-Dist: pandas (>=2.2.3,<3.0.0)
Requires-Dist: protobuf (>=5.29.0,<6.0.0)
Requires-Dist: pydantic (>=2.10.2,<3.0.0)
Requires-Dist: pynacl (>=1.5.0,<2.0.0)
Requires-Dist: requests (>=2.32.3,<3.0.0)
